faire/__init__.py
faire/hello_world.py
faire-0.0.2rc16.post1.dist-info/licenses/LICENSE
faire-0.0.2rc16.post1.dist-info/WHEEL
faire-0.0.2rc16.post1.dist-info/METADATA
faire-0.0.2rc16.post1.dist-info/RECORD
